Sync_FiFo/sync_fifo.sv
// -----------------------------------------------------------------------------
// Synchronous FIFO
// - Single clock domain
// - Registered read data (1-cycle latency from read_en to valid read_data)
// - Parameterizable data width and depth (depth must be power of 2)
// -----------------------------------------------------------------------------

module sync_fifo #(
    parameter DATA_WIDTH = 8,
    parameter DEPTH      = 16,                  // must be power of 2
    parameter ADDR_WIDTH = $clog2(DEPTH)
)(
    input  wire                   clk,
    input  wire                   rst_n,        // active-low synchronous reset

    // Write interface
    input  wire                   wr_en,
    input  wire [DATA_WIDTH-1:0]  wr_data,
    output wire                   full,

    // Read interface
    input  wire                   rd_en,
    output reg  [DATA_WIDTH-1:0]  rd_data,
    output wire                   empty
);

    // Memory array
    reg [DATA_WIDTH-1:0] mem [0:DEPTH-1];

    // Pointers: one extra MSB bit to distinguish full vs empty
    reg [ADDR_WIDTH:0] wr_ptr;
    reg [ADDR_WIDTH:0] rd_ptr;

    wire [ADDR_WIDTH-1:0] wr_addr = wr_ptr[ADDR_WIDTH-1:0];
    wire [ADDR_WIDTH-1:0] rd_addr = rd_ptr[ADDR_WIDTH-1:0];

    // Full:  pointers equal except MSB differs (wrapped around)
    // Empty: pointers exactly equal
    assign full  = (wr_ptr[ADDR_WIDTH] != rd_ptr[ADDR_WIDTH]) &&
                   (wr_addr == rd_addr);
    assign empty = (wr_ptr == rd_ptr);

    wire wr_valid = wr_en & ~full;
    wire rd_valid = rd_en & ~empty;

    // Write logic
    always @(posedge clk) begin
        if (!rst_n) begin
            wr_ptr <= 0;
        end else if (wr_valid) begin
            mem[wr_addr] <= wr_data;
            wr_ptr       <= wr_ptr + 1'b1;
        end
    end

    // Read logic (registered output -> 1 cycle latency)
    always @(posedge clk) begin
        if (!rst_n) begin
            rd_ptr  <= 0;
            rd_data <= {DATA_WIDTH{1'b0}};
        end else if (rd_valid) begin
            rd_data <= mem[rd_addr];
            rd_ptr  <= rd_ptr + 1'b1;
        end
    end

endmodule

Sync_FiFo/tb_sync_fifo.sv
`timescale 1ns / 1ps
module tb_sync_fifo;
    parameter DATA_WIDTH = 8;
    parameter FIFO_DEPTH = 16;

    reg clk;
    reg rst_n;
    reg wr_en;
    reg rd_en;
    reg [DATA_WIDTH-1:0] wr_data;
    wire [DATA_WIDTH-1:0] rd_data;
    wire full;
    wire empty;
    integer i;

    // Instantiate the sync_fifo
    sync_fifo #(
        .DATA_WIDTH(DATA_WIDTH),
        .DEPTH(FIFO_DEPTH)
    ) uut (
        .clk(clk),
        .rst_n(rst_n),
        .wr_en(wr_en),
        .wr_data(wr_data),
        .full(full),
        .rd_en(rd_en),
        .rd_data(rd_data),
        .empty(empty)
    );

    // Clock generation
    initial begin
        clk = 0;
        // forever #5 clk = ~clk; // 100MHz clock
    end

    always #5 clk = ~clk; // 100MHz clock

        // Debug: trace internal FIFO signals every clock edge (hierarchical reference)
    always @(posedge clk) begin
        #1; // wait for nonblocking assignments to settle
        $display("DBG t=%0t rd_en=%b empty=%b rd_valid=%b rd_ptr=%0d wr_ptr=%0d rd_addr=%0d rd_data=%0h",
                $time, rd_en, empty, uut.rd_valid, uut.rd_ptr, uut.wr_ptr, uut.rd_addr, uut.rd_data);
    end
    initial begin
        $dumpfile("tb_sync_fifo.vcd");
        $dumpvars(0, tb_sync_fifo);
        // $monitor("time=%0t wr_en=%b rd_en=%b wr_data=%02h rd_data=%02h full=%b empty=%b",
                //  $time, wr_en, rd_en, wr_data, rd_data, full, empty);

        // Reset the FIFO
        rst_n = 0;
        wr_en = 0;
        rd_en = 0;
        wr_data = 0;
        #20 rst_n = 1;

        // ---------------------------------------------------------------
        // Write data to the FIFO
        // Fix: set wr_data BEFORE the clock edge that samples it, so the
        // value written into memory on this edge is the one we intended.
        // ---------------------------------------------------------------
        wr_en = 1;
        for (i = 0; i < FIFO_DEPTH; i = i + 1) begin
            wr_data = $random % 256; // set data first
            @(posedge clk);          // this edge writes wr_data into mem
            if (full) $display("FIFO is full at time %t", $time);
        end
        wr_en = 0;

        // ---------------------------------------------------------------
        // Read data from the FIFO
        // Fix: add #1 after @(posedge clk) so the DUT's nonblocking
        // assignment (rd_data <= mem[rd_addr]) has settled before we
        // sample rd_data. Without this, we read the PREVIOUS rd_data.
        rd_en = 1;
        @(posedge clk);
        @(posedge clk);
        @(posedge clk);
        @(posedge clk);
        @(posedge clk);
        @(posedge clk);
        rd_en = 0;
        // ---------------------------------------------------------------
        // Simultaneous write + read check
        // ---------------------------------------------------------------
        wr_data = 8'hAA;
        wr_en   = 1;
        @(posedge clk);

        wr_data = 8'hBB;
        rd_en   = 1;
        @(posedge clk);
        #1;
        // $display("Simultaneous R/W -> Read data: %0h at time %t", rd_data, $time);

        wr_en = 0;
        rd_en = 0;
        @(posedge clk);
        @(posedge clk);

        $display("Test complete.");
        $finish;
    end
endmodule

Sync_FiFo/tb_sync_fifo.vcd
$date
	Sat Aug 01 13:16:44 2026
$end
$version
	Icarus Verilog
$end
$timescale
	1ps
$end
$scope module tb_sync_fifo $end
$var wire 8 ! rd_data [7:0] $end
$var wire 1 " full $end
$var wire 1 # empty $end
$var parameter 32 $ DATA_WIDTH $end
$var parameter 32 % FIFO_DEPTH $end
$var reg 1 & clk $end
$var reg 1 ' rd_en $end
$var reg 1 ( rst_n $end
$var reg 8 ) wr_data [7:0] $end
$var reg 1 * wr_en $end
$var integer 32 + i [31:0] $end
$scope module uut $end
$var wire 1 & clk $end
$var wire 1 " full $end
$var wire 1 ' rd_en $end
$var wire 1 , rd_valid $end
$var wire 1 ( rst_n $end
$var wire 8 - wr_data [7:0] $end
$var wire 1 * wr_en $end
$var wire 1 . wr_valid $end
$var wire 4 / wr_addr [3:0] $end
$var wire 4 0 rd_addr [3:0] $end
$var wire 1 # empty $end
$var parameter 32 1 ADDR_WIDTH $end
$var parameter 32 2 DATA_WIDTH $end
$var parameter 32 3 DEPTH $end
$var reg 8 4 rd_data [7:0] $end
$var reg 5 5 rd_ptr [4:0] $end
$var reg 5 6 wr_ptr [4:0] $end
$upscope $end
$upscope $end
$enddefinitions $end
$comment Show the parameter values. $end
$dumpall
b10000 3
b1000 2
b100 1
b10000 %
b1000 $
$end
#0
$dumpvars
bx 6
bx 5
bx 4
bx 0
bx /
0.
b0 -
0,
bx +
0*
b0 )
0(
0'
0&
x#
x"
bx !
$end
#5000
0"
b0 /
b0 0
1#
b0 6
b0 !
b0 4
b0 5
1&
#10000
0&
#15000
1&
#20000
1.
0&
b100100 )
b100100 -
b0 +
1*
1(
#25000
b1 /
0#
b1 6
b10000001 )
b10000001 -
b1 +
1&
#30000
0&
#35000
b10 /
b10 6
b1001 )
b1001 -
b10 +
1&
#40000
0&
#45000
b11 /
b11 6
b1100011 )
b1100011 -
b11 +
1&
#50000
0&
#55000
b100 /
b100 6
b1101 )
b1101 -
b100 +
1&
#60000
0&
#65000
b101 /
b101 6
b10001101 )
b10001101 -
b101 +
1&
#70000
0&
#75000
b110 /
b110 6
b1100101 )
b1100101 -
b110 +
1&
#80000
0&
#85000
b111 /
b111 6
b10010 )
b10010 -
b111 +
1&
#90000
0&
#95000
b1000 /
b1000 6
b1 )
b1 -
b1000 +
1&
#100000
0&
#105000
b1001 /
b1001 6
b1101 )
b1101 -
b1001 +
1&
#110000
0&
#115000
b1010 /
b1010 6
b1110110 )
b1110110 -
b1010 +
1&
#120000
0&
#125000
b1011 /
b1011 6
b111101 )
b111101 -
b1011 +
1&
#130000
0&
#135000
b1100 /
b1100 6
b11101101 )
b11101101 -
b1100 +
1&
#140000
0&
#145000
b1101 /
b1101 6
b10001100 )
b10001100 -
b1101 +
1&
#150000
0&
#155000
b1110 /
b1110 6
b11111001 )
b11111001 -
b1110 +
1&
#160000
0&
#165000
b1111 /
b1111 6
b11000110 )
b11000110 -
b1111 +
1&
#170000
0&
#175000
1"
b0 /
b10000 6
1,
0.
1'
0*
b10000 +
1&
#180000
0&
#185000
0"
b1 0
b1 5
b10000001 !
b10000001 4
1&
#190000
0&
#195000
b10 0
b10 5
1&
#200000
0&
#205000
b11 0
b11 5
b1100011 !
b1100011 4
1&
#210000
0&
#215000
b100 0
b100 5
1&
#220000
0&
#225000
b101 0
b101 5
b10001101 !
b10001101 4
1&
#230000
0&
#235000
b110 0
b110 5
1.
0,
1*
b10101010 )
b10101010 -
0'
1&
#240000
0&
#245000
b1 /
b10001 6
1,
1'
b10111011 )
b10111011 -
1&
#250000
0&
#255000
b111 0
b10 /
b111 5
b10010 !
b10010 4
b10010 6
1&
#256000
0,
0.
0'
0*
