ALU/alu.sv
// Simple 8-bit ALU
module alu (
    input  wire [7:0] a,
    input  wire [7:0] b,
    input  wire [2:0] op,
    output reg  [7:0] result,
    output wire       carry_out,
    output wire       zero
);

    assign carry_out = (op == 3'b000) ? (a + b > 8'hFF) : 1'b0;
    assign zero      = (result == 8'h00);

    always @(*) begin
        case (op)
            3'b000: result = a + b;          // ADD
            3'b001: result = a - b;          // SUB
            3'b010: result = a & b;          // AND
            3'b011: result = a | b;          // OR
            3'b100: result = a ^ b;          // XOR
            3'b101: result = ~a;             // NOT A
            3'b110: result = (a < b) ? 8'h01 : 8'h00; // Compare less than
            default: result = 8'h00;         // NOP / unsupported
        endcase
    end

endmodule

ALU/tb_alu.sv
`timescale 1ns/1ps

module tb_alu;
    reg [7:0] a;
    reg [7:0] b;
    reg [2:0] op;
    wire [7:0] result;
    wire carry_out;
    wire zero;

    // Instantiate the ALU
    alu uut (
        .a(a),
        .b(b),
        .op(op),
        .result(result),
        .carry_out(carry_out),
        .zero(zero)
    );

    initial begin
        $dumpfile("tb_alu.vcd");
        $dumpvars(0, tb_alu);

        $display("Time   op  a      b      result  carry zero");
        $display("------------------------------------------------");

        a = 8'h10; b = 8'h20; op = 3'b000; // ADD
        #10 $display("%4dns  %b  %h  %h  %h      %b     %b", $time, op, a, b, result, carry_out, zero);

        a = 8'h50; b = 8'h30; op = 3'b001; // SUB
        #10 $display("%4dns  %b  %h  %h  %h      %b     %b", $time, op, a, b, result, carry_out, zero);

        a = 8'hF0; b = 8'h20; op = 3'b000; // ADD with carry
        #10 $display("%4dns  %b  %h  %h  %h      %b     %b", $time, op, a, b, result, carry_out, zero);

        a = 8'hAA; b = 8'h55; op = 3'b010; // AND
        #10 $display("%4dns  %b  %h  %h  %h      %b     %b", $time, op, a, b, result, carry_out, zero);

        a = 8'hAA; b = 8'h55; op = 3'b011; // OR
        #10 $display("%4dns  %b  %h  %h  %h      %b     %b", $time, op, a, b, result, carry_out, zero);

        a = 8'hFF; b = 8'h0F; op = 3'b100; // XOR
        #10 $display("%4dns  %b  %h  %h  %h      %b     %b", $time, op, a, b, result, carry_out, zero);

        a = 8'h0F; b = 8'hF0; op = 3'b101; // NOT A
        #10 $display("%4dns  %b  %h  %h  %h      %b     %b", $time, op, a, b, result, carry_out, zero);

        a = 8'h05; b = 8'h0A; op = 3'b110; // Compare less than
        #10 $display("%4dns  %b  %h  %h  %h      %b     %b", $time, op, a, b, result, carry_out, zero);

        a = 8'h0A; b = 8'h05; op = 3'b110; // Compare less than false
        #10 $display("%4dns  %b  %h  %h  %h      %b     %b", $time, op, a, b, result, carry_out, zero);

        $display("Test complete.");
        $finish;
    end
endmodule

ALU/tb_alu.vcd
$date
	Sat Jul 25 13:04:51 2026
$end
$version
	Icarus Verilog
$end
$timescale
	1ps
$end
$scope module tb_alu $end
$var wire 1 ! zero $end
$var wire 8 " result [7:0] $end
$var wire 1 # carry_out $end
$var reg 8 $ a [7:0] $end
$var reg 8 % b [7:0] $end
$var reg 3 & op [2:0] $end
$scope module uut $end
$var wire 8 ' a [7:0] $end
$var wire 8 ( b [7:0] $end
$var wire 3 ) op [2:0] $end
$var wire 1 ! zero $end
$var wire 1 # carry_out $end
$var reg 8 * result [7:0] $end
$upscope $end
$upscope $end
$enddefinitions $end
$comment Show the parameter values. $end
$dumpall
$end
#0
$dumpvars
b110000 *
b0 )
b100000 (
b10000 '
b0 &
b100000 %
b10000 $
0#
b110000 "
0!
$end
#10000
b100000 "
b100000 *
b1 &
b1 )
b110000 %
b110000 (
b1010000 $
b1010000 '
#20000
b10000 "
b10000 *
b0 &
b0 )
b100000 %
b100000 (
b11110000 $
b11110000 '
#30000
1!
b0 "
b0 *
b10 &
b10 )
b1010101 %
b1010101 (
b10101010 $
b10101010 '
#40000
0!
b11111111 "
b11111111 *
b11 &
b11 )
#50000
b11110000 "
b11110000 *
b100 &
b100 )
b1111 %
b1111 (
b11111111 $
b11111111 '
#60000
b101 &
b101 )
b11110000 %
b11110000 (
b1111 $
b1111 '
#70000
b1 "
b1 *
b110 &
b110 )
b1010 %
b1010 (
b101 $
b101 '
#80000
1!
b0 "
b0 *
b101 %
b101 (
b1010 $
b1010 '
